check_requirements_txt/__about__.py
check_requirements_txt/__init__.py
check_requirements_txt/__main__.py
check_requirements_txt-1.4.1.dist-info/METADATA
check_requirements_txt-1.4.1.dist-info/WHEEL
check_requirements_txt-1.4.1.dist-info/entry_points.txt
check_requirements_txt-1.4.1.dist-info/licenses/LICENSE.txt
check_requirements_txt-1.4.1.dist-info/RECORD
