Metadata-Version: 2.4
Name: check-requirements-txt
Version: 1.4.1
Summary: A tool (and also a pre-commit hook) to automatically check the missing packages in requirements.txt and pyproject.toml.
Project-URL: Documentation, https://github.com/ferstar/check-requirements-txt#readme
Project-URL: Issues, https://github.com/ferstar/check-requirements-txt/issues
Project-URL: Source, https://github.com/ferstar/check-requirements-txt
Author-email: ferstar <zhangjianfei3@gmail.com>
License-Expression: MIT
License-File: LICENSE.txt
Classifier: Programming Language :: Python
Classifier: Programming Language :: Python :: 3.10
Classifier: Programming Language :: Python :: 3.11
Classifier: Programming Language :: Python :: 3.12
Classifier: Programming Language :: Python :: 3.13
Classifier: Programming Language :: Python :: 3.14
Classifier: Programming Language :: Python :: Implementation :: CPython
Classifier: Programming Language :: Python :: Implementation :: PyPy
Requires-Python: >=3.10
Requires-Dist: packaging
Requires-Dist: tomli>=1.2.0; python_version < '3.11'
